README.md
setup.py
chemical/__init__.py
chemical/aggregators.py
chemical/iterators.py
chemical.egg-info/PKG-INFO
chemical.egg-info/SOURCES.txt
chemical.egg-info/dependency_links.txt
chemical.egg-info/top_level.txt