Metadata-Version: 2.1
Name: chemical
Version: 1.0.1
Summary: Rust-style iterators for Python!
Home-page: http://github.com/Pebaz/Chemical
Author: http://github.com/Pebaz
License: MIT
Platform: UNKNOWN
Requires-Python: >=3.6.0
